gym_leftright/__init__.py
gym_leftright/envs/__init__.py
gym_leftright/envs/leftright_env.py
gym_leftright/test/test_leftrighenv.py
gym_leftright/test/__init__.py
gym_leftright-0.0.2.dist-info/top_level.txt
gym_leftright-0.0.2.dist-info/metadata.json
gym_leftright-0.0.2.dist-info/DESCRIPTION.rst
gym_leftright-0.0.2.dist-info/RECORD
gym_leftright-0.0.2.dist-info/WHEEL
gym_leftright-0.0.2.dist-info/METADATA
