Metadata-Version: 2.0
Name: gym-leftright
Version: 0.0.2
Summary: Left or right control environment for openai/gym
Home-page: https://github.com/gpldecha/gym-leftright
Author: Guillaume de Chambrier
Author-email: chambrierg@gmail.com
License: MIT
Platform: UNKNOWN
Requires-Dist: gym
